cognitiveoak/__init__.py
cognitiveoak/apis.py
cognitiveoak/test/__init__.py
cognitiveoak/test/example.py
cognitiveoak/utils/__init__.py
cognitiveoak/utils/classes.py
cognitiveoak-1.0.1.dist-info/LICENSE
cognitiveoak-1.0.1.dist-info/METADATA
cognitiveoak-1.0.1.dist-info/WHEEL
cognitiveoak-1.0.1.dist-info/top_level.txt
cognitiveoak-1.0.1.dist-info/RECORD
