Metadata-Version: 2.1
Name: cognitiveoak
Version: 1.0.1
Summary: A python client for CognitiveOak platform.
Home-page: https://github.com/unsw-cse-soc/CognitiveOak-PythonSDK.git
Author: Shayan Zamanirad
Author-email: shayane.zamani@gmail.com
License: UNKNOWN
Keywords: core package
Platform: UNKNOWN
Classifier: Programming Language :: Python :: 3
Classifier: License :: OSI Approved :: MIT License
Classifier: Operating System :: OS Independent
